easyrv/__init__.py
easyrv/camera_operate.py
easyrv/data_make.py
easyrv/data_move.py
easyrv/easy_os.py
easyrv/image_draw.py
easyrv/image_trans.py
easyrv/rv_hello.py
easyrv/MvImport/CameraParams_const.py
easyrv/MvImport/CameraParams_header.py
easyrv/MvImport/MvCameraControl_class.py
easyrv/MvImport/MvCameraControl_header.py
easyrv/MvImport/MvErrorDefine_const.py
easyrv/MvImport/PixelType_const.py
easyrv/MvImport/PixelType_header.py
easyrv/MvImport/__init__.py
easyrv-0.1.12.dist-info/METADATA
easyrv-0.1.12.dist-info/WHEEL
easyrv-0.1.12.dist-info/top_level.txt
easyrv-0.1.12.dist-info/RECORD
