Metadata-Version: 2.1
Name: easyrv
Version: 0.1.12
Summary: 自制用于机器人视觉的库
Home-page: UNKNOWN
Author: xwy
Author-email: x211481@163.com
License: UNKNOWN
Platform: UNKNOWN
Classifier: Programming Language :: Python :: 3
Classifier: License :: OSI Approved :: MIT License
Classifier: Operating System :: OS Independent
